switchto.py
switchto-0.0.3.dist-info/LICENSE
switchto-0.0.3.dist-info/METADATA
switchto-0.0.3.dist-info/WHEEL
switchto-0.0.3.dist-info/top_level.txt
switchto-0.0.3.dist-info/RECORD
